import java.io.BufferedReader;
import java.io.FileReader;
import java.io.FileWriter;

public class FileUtils
{
  static BufferedReader br = null;
  static FileReader fr = null;
  static FileWriter fw = null;
  
  /* Error */
  public String ObtenerNombre(String ruta_Actual)
  {
    // Byte code:
    //   0: ldc 29
    //   2: astore_2
    //   3: new 31	java/io/FileReader
    //   6: dup
    //   7: aload_1
    //   8: invokespecial 33	java/io/FileReader:<init>	(Ljava/lang/String;)V
    //   11: putstatic 16	FileUtils:fr	Ljava/io/FileReader;
    //   14: new 36	java/io/BufferedReader
    //   17: dup
    //   18: getstatic 16	FileUtils:fr	Ljava/io/FileReader;
    //   21: invokespecial 38	java/io/BufferedReader:<init>	(Ljava/io/Reader;)V
    //   24: putstatic 14	FileUtils:br	Ljava/io/BufferedReader;
    //   27: getstatic 14	FileUtils:br	Ljava/io/BufferedReader;
    //   30: invokevirtual 41	java/io/BufferedReader:readLine	()Ljava/lang/String;
    //   33: astore_2
    //   34: goto +86 -> 120
    //   37: astore_3
    //   38: getstatic 45	java/lang/System:out	Ljava/io/PrintStream;
    //   41: aload_3
    //   42: invokevirtual 51	java/lang/Exception:getMessage	()Ljava/lang/String;
    //   45: invokevirtual 56	java/io/PrintStream:println	(Ljava/lang/String;)V
    //   48: getstatic 16	FileUtils:fr	Ljava/io/FileReader;
    //   51: invokevirtual 61	java/io/FileReader:close	()V
    //   54: goto +10 -> 64
    //   57: astore 5
    //   59: aload 5
    //   61: invokevirtual 64	java/io/IOException:printStackTrace	()V
    //   64: getstatic 14	FileUtils:br	Ljava/io/BufferedReader;
    //   67: invokevirtual 69	java/io/BufferedReader:close	()V
    //   70: goto +82 -> 152
    //   73: astore 5
    //   75: aload 5
    //   77: invokevirtual 64	java/io/IOException:printStackTrace	()V
    //   80: goto +72 -> 152
    //   83: astore 4
    //   85: getstatic 16	FileUtils:fr	Ljava/io/FileReader;
    //   88: invokevirtual 61	java/io/FileReader:close	()V
    //   91: goto +10 -> 101
    //   94: astore 5
    //   96: aload 5
    //   98: invokevirtual 64	java/io/IOException:printStackTrace	()V
    //   101: getstatic 14	FileUtils:br	Ljava/io/BufferedReader;
    //   104: invokevirtual 69	java/io/BufferedReader:close	()V
    //   107: goto +10 -> 117
    //   110: astore 5
    //   112: aload 5
    //   114: invokevirtual 64	java/io/IOException:printStackTrace	()V
    //   117: aload 4
    //   119: athrow
    //   120: getstatic 16	FileUtils:fr	Ljava/io/FileReader;
    //   123: invokevirtual 61	java/io/FileReader:close	()V
    //   126: goto +10 -> 136
    //   129: astore 5
    //   131: aload 5
    //   133: invokevirtual 64	java/io/IOException:printStackTrace	()V
    //   136: getstatic 14	FileUtils:br	Ljava/io/BufferedReader;
    //   139: invokevirtual 69	java/io/BufferedReader:close	()V
    //   142: goto +10 -> 152
    //   145: astore 5
    //   147: aload 5
    //   149: invokevirtual 64	java/io/IOException:printStackTrace	()V
    //   152: aload_2
    //   153: areturn
    // Line number table:
    //   Java source line #27	-> byte code offset #0
    //   Java source line #30	-> byte code offset #3
    //   Java source line #31	-> byte code offset #14
    //   Java source line #32	-> byte code offset #27
    //   Java source line #33	-> byte code offset #34
    //   Java source line #34	-> byte code offset #37
    //   Java source line #36	-> byte code offset #38
    //   Java source line #42	-> byte code offset #48
    //   Java source line #43	-> byte code offset #54
    //   Java source line #45	-> byte code offset #59
    //   Java source line #48	-> byte code offset #64
    //   Java source line #49	-> byte code offset #70
    //   Java source line #51	-> byte code offset #75
    //   Java source line #40	-> byte code offset #83
    //   Java source line #42	-> byte code offset #85
    //   Java source line #43	-> byte code offset #91
    //   Java source line #45	-> byte code offset #96
    //   Java source line #48	-> byte code offset #101
    //   Java source line #49	-> byte code offset #107
    //   Java source line #51	-> byte code offset #112
    //   Java source line #53	-> byte code offset #117
    //   Java source line #42	-> byte code offset #120
    //   Java source line #43	-> byte code offset #126
    //   Java source line #45	-> byte code offset #131
    //   Java source line #48	-> byte code offset #136
    //   Java source line #49	-> byte code offset #142
    //   Java source line #51	-> byte code offset #147
    //   Java source line #54	-> byte code offset #152
    // Local variable table:
    //   start	length	slot	name	signature
    //   0	154	0	this	FileUtils
    //   0	154	1	ruta_Actual	String
    //   2	151	2	nombre	String
    //   37	5	3	e	Exception
    //   83	35	4	localObject	Object
    //   57	3	5	e	java.io.IOException
    //   73	3	5	e	java.io.IOException
    //   94	3	5	e	java.io.IOException
    //   110	3	5	e	java.io.IOException
    //   129	3	5	e	java.io.IOException
    //   145	3	5	e	java.io.IOException
    // Exception table:
    //   from	to	target	type
    //   3	34	37	java/lang/Exception
    //   48	54	57	java/io/IOException
    //   64	70	73	java/io/IOException
    //   3	48	83	finally
    //   85	91	94	java/io/IOException
    //   101	107	110	java/io/IOException
    //   120	126	129	java/io/IOException
    //   136	142	145	java/io/IOException
  }
}
